webAssist.py
web_assist-0.0.5.dist-info/METADATA
web_assist-0.0.5.dist-info/WHEEL
web_assist-0.0.5.dist-info/top_level.txt
web_assist-0.0.5.dist-info/RECORD
