Metadata-Version: 2.1
Name: web-assist
Version: 0.0.5
Summary: Tools for scraping and downloading internet resources
Home-page: https://github.com/pytholabsbot1/web-assist
Author: Pytholabs
Author-email: info@pytholabs.com
License: UNKNOWN
Platform: UNKNOWN
Requires-Dist: requests
